quantfolio/Portfolio.py
quantfolio/__init__.py
quantfolio/Optimizers/BayesianOptimizer.py
quantfolio/Optimizers/MonteCarloOptimizer.py
quantfolio/Optimizers/MonteCarloStatsOptimizer.py
quantfolio/Optimizers/OptimisationResults.py
quantfolio/Optimizers/SLSQPStatsOptimizer.py
quantfolio/Optimizers/__init__.py
quantfolio/Optimizers/utils.py
quantfolio-0.3.2.dist-info/LICENSE
quantfolio-0.3.2.dist-info/METADATA
quantfolio-0.3.2.dist-info/WHEEL
quantfolio-0.3.2.dist-info/top_level.txt
quantfolio-0.3.2.dist-info/RECORD
